djangocms_uikit/__init__.py
djangocms_uikit/admin.py
djangocms_uikit/apps.py
djangocms_uikit/cms_plugins.py
djangocms_uikit/models.py
djangocms_uikit/tests.py
djangocms_uikit/views.py
djangocms_uikit/migrations/0001_initial.py
djangocms_uikit/migrations/0002_auto_20190809_1421.py
djangocms_uikit/migrations/0003_uksectionmodel_style2.py
djangocms_uikit/migrations/0004_remove_uksectionmodel_style2.py
djangocms_uikit/migrations/0005_auto_20190809_1428.py
djangocms_uikit/migrations/0006_cardspluginmodel_style.py
djangocms_uikit/migrations/0007_cardspluginmodel_hover.py
djangocms_uikit/migrations/0008_cardspluginmodel_size.py
djangocms_uikit/migrations/0009_auto_20190809_1522.py
djangocms_uikit/migrations/__init__.py
djangocms_uikit/templates/djangocms_uikit/test.html
djangocms_uikit/templates/djangocms_uikit/uk-accordion.html
djangocms_uikit/templates/djangocms_uikit/uk-accordion_items.html
djangocms_uikit/templates/djangocms_uikit/uk-cards.html
djangocms_uikit/templates/djangocms_uikit/uk-container.html
djangocms_uikit/templates/djangocms_uikit/uk-grid.html
djangocms_uikit/templates/djangocms_uikit/uk-section.html
djangocms_uikit-0.1.3.dist-info/LICENSE
djangocms_uikit-0.1.3.dist-info/METADATA
djangocms_uikit-0.1.3.dist-info/WHEEL
djangocms_uikit-0.1.3.dist-info/top_level.txt
djangocms_uikit-0.1.3.dist-info/RECORD
