Metadata-Version: 2.1
Name: djangocms-uikit
Version: 0.1.3
Summary: A UiKit Plugin for the DjangoCMS Framework
Home-page: https://github.com/domlysi/djangocms-uikit
Author: Dominik Lysiak
Author-email: dominik.lysiak@freenet.de
License: BSD License
Platform: UNKNOWN
Classifier: Environment :: Web Environment
Classifier: Framework :: Django
Classifier: Framework :: Django :: 2.1
Classifier: Intended Audience :: Developers
Classifier: License :: OSI Approved :: BSD License
Classifier: Operating System :: OS Independent
Classifier: Programming Language :: Python
Classifier: Programming Language :: Python :: 3.5
Classifier: Programming Language :: Python :: 3.6
Classifier: Topic :: Internet :: WWW/HTTP
Classifier: Topic :: Internet :: WWW/HTTP :: Dynamic Content
